bitorch/__init__.py
bitorch/config.py
bitorch/runtime_mode.py
bitorch/util.py
bitorch/layers/__init__.py
bitorch/layers/bembedding.py
bitorch/layers/config.py
bitorch/layers/debug_layers.py
bitorch/layers/pact.py
bitorch/layers/pad.py
bitorch/layers/qactivation.py
bitorch/layers/qconv1d.py
bitorch/layers/qconv2d.py
bitorch/layers/qconv3d.py
bitorch/layers/qconv_mixin.py
bitorch/layers/qembedding.py
bitorch/layers/qlinear.py
bitorch/layers/register.py
bitorch/layers/extensions/__init__.py
bitorch/layers/extensions/layer_container.py
bitorch/layers/extensions/layer_implementation.py
bitorch/layers/extensions/layer_recipe.py
bitorch/layers/extensions/layer_registration.py
bitorch/layers/extensions/layer_registry.py
bitorch/models/__init__.py
bitorch/models/base.py
bitorch/models/common_layers.py
bitorch/models/densenet.py
bitorch/models/dlrm.py
bitorch/models/lenet.py
bitorch/models/meliusnet.py
bitorch/models/model_hub.py
bitorch/models/quicknet.py
bitorch/models/resnet.py
bitorch/models/resnet_e.py
bitorch/quantizations/__init__.py
bitorch/quantizations/approx_sign.py
bitorch/quantizations/base.py
bitorch/quantizations/config.py
bitorch/quantizations/dorefa.py
bitorch/quantizations/identity.py
bitorch/quantizations/progressive_sign.py
bitorch/quantizations/quantization_scheduler.py
bitorch/quantizations/sign.py
bitorch/quantizations/ste_heaviside.py
bitorch/quantizations/swish_sign.py
bitorch-0.4.1.data/data/AUTHORS
bitorch-0.4.1.data/data/CHANGELOG.md
bitorch-0.4.1.data/data/README.md
bitorch-0.4.1.data/data/mypy.ini
bitorch-0.4.1.data/data/requirements-dev.txt
bitorch-0.4.1.data/data/requirements.txt
bitorch-0.4.1.data/data/version.txt
examples/__init__.py
examples/dlrm/__init__.py
examples/dlrm/train_dlrm.py
examples/dlrm/datasets/__init__.py
examples/dlrm/datasets/base.py
examples/dlrm/datasets/criteo.py
examples/dlrm/datasets/dummy_dataset.py
examples/dlrm/facebook_dataloading/__init__.py
examples/dlrm/facebook_dataloading/data_utils.py
bitorch-0.4.1.dist-info/LICENSE
bitorch-0.4.1.dist-info/METADATA
bitorch-0.4.1.dist-info/WHEEL
bitorch-0.4.1.dist-info/top_level.txt
bitorch-0.4.1.dist-info/RECORD
