Metadata-Version: 2.1
Name: bitorch
Version: 0.4.1
Summary: A package for building and training quantized and binary neural networks with Pytorch
Home-page: https://github.com/hpi-xnor/bitorch
Author: Hasso Plattner Institute
Author-email: fb10-xnor@hpi.de
Classifier: Development Status :: 3 - Alpha
Classifier: Intended Audience :: Developers
Classifier: License :: OSI Approved :: GNU General Public License v3 or later (GPLv3+)
Classifier: Operating System :: OS Independent
Classifier: Programming Language :: Python :: 3 :: Only
Classifier: Programming Language :: Python :: 3.7
Classifier: Programming Language :: Python :: 3.8
Classifier: Programming Language :: Python :: 3.9
Classifier: Programming Language :: Python :: 3.10
Requires-Python: >=3.7
License-File: LICENSE
Requires-Dist: torch >=1.9.0
Requires-Dist: matplotlib
Requires-Dist: numpy
Requires-Dist: pandas
Provides-Extra: dev
Requires-Dist: black ; extra == 'dev'
Requires-Dist: build ; extra == 'dev'
Requires-Dist: importlib-metadata ==4.13.0 ; extra == 'dev'
Requires-Dist: flake8 ; extra == 'dev'
Requires-Dist: flake8-docstrings ; extra == 'dev'
Requires-Dist: importlib-metadata <5 ; extra == 'dev'
Requires-Dist: mypy ~=0.920 ; extra == 'dev'
Requires-Dist: myst-nb ; extra == 'dev'
Requires-Dist: nbclient ==0.5.13 ; extra == 'dev'
Requires-Dist: nbsphinx-link ==1.3.0 ; extra == 'dev'
Requires-Dist: nbsphinx ==0.8.8 ; extra == 'dev'
Requires-Dist: pep8-naming ; extra == 'dev'
Requires-Dist: pre-commit ; extra == 'dev'
Requires-Dist: pytest ; extra == 'dev'
Requires-Dist: pytest-cov ; extra == 'dev'
Requires-Dist: sphinx ; extra == 'dev'
Requires-Dist: twine ; extra == 'dev'
Provides-Extra: opt
Requires-Dist: fvbitcore ; extra == 'opt'
Requires-Dist: pytorch-lightning >=2.0.1 ; extra == 'opt'
Requires-Dist: torchvision >=0.10.0 ; extra == 'opt'
Requires-Dist: sklearn ; extra == 'opt'
Requires-Dist: wandb ~=0.12.0 ; extra == 'opt'
Requires-Dist: tensorboard ; extra == 'opt'
Requires-Dist: jsonargparse[signatures] ; extra == 'opt'
Requires-Dist: bitorch ; extra == 'opt'
Requires-Dist: bitorch-engine ; extra == 'opt'
